softwareai/Chat.py
softwareai/ChatConvert.py
softwareai/Editor.py
softwareai/EditorConvert.py
softwareai/SoftwareAIWeb.py
softwareai/__init__.py
softwareai/softwareai_cli.py
softwareai/CoreApp/_init_Instructions_.py
softwareai/CoreApp/_init_agents_.py
softwareai/CoreApp/_init_core_.py
softwareai/CoreApp/_init_environment_.py
softwareai/CoreApp/_init_functions_.py
softwareai/CoreApp/_init_keys_.py
softwareai/CoreApp/_init_libs_.py
softwareai/CoreApp/_init_paths_.py
softwareai/CoreApp/_init_submit_outputs_.py
softwareai/CoreApp/_init_tools_.py
softwareai/CoreApp/environment.env
softwareai/CoreApp/environment.txt
softwareai/CoreApp/projectstructure.txt
softwareai/CoreApp/Agents/Company_CEO/ByteManager.py
softwareai/CoreApp/Agents/Company_CEO/__pycache__/AI_ByteManager_Company_CEO.cpython-39.pyc
softwareai/CoreApp/Agents/Company_CEO/__pycache__/ByteManager.cpython-39.pyc
softwareai/CoreApp/Agents/Company_Managers/AI_MatrixAI_Company_Owners.py
softwareai/CoreApp/Agents/Company_Managers/AI_MatrixMinder_Company_Managers.py
softwareai/CoreApp/Agents/Company_Managers/__pycache__/AI_MatrixMinder_Company_Managers.cpython-39.pyc
softwareai/CoreApp/Agents/Pre_Project/Tigrao.py
softwareai/CoreApp/Agents/Pre_Project/__pycache__/AI_Tigrao_Pre_Project.cpython-39.pyc
softwareai/CoreApp/Agents/Pre_Project/__pycache__/Tigrao.cpython-39.pyc
softwareai/CoreApp/Agents/Software_Development/DataWeaver.py
softwareai/CoreApp/Agents/Software_Development/QuantumCore.py
softwareai/CoreApp/Agents/Software_Development/SignalMaster.py
softwareai/CoreApp/Agents/Software_Development/__pycache__/AI_DataWeaver_Software_Development.cpython-39.pyc
softwareai/CoreApp/Agents/Software_Development/__pycache__/AI_NexGenCoder_Software_Development.cpython-39.pyc
softwareai/CoreApp/Agents/Software_Development/__pycache__/AI_QuantumCore_Software_Development.cpython-39.pyc
softwareai/CoreApp/Agents/Software_Development/__pycache__/AI_SignalMaster_Software_Development.cpython-39.pyc
softwareai-0.5.73.dist-info/LICENSE.txt
softwareai-0.5.73.dist-info/METADATA
softwareai-0.5.73.dist-info/WHEEL
softwareai-0.5.73.dist-info/entry_points.txt
softwareai-0.5.73.dist-info/top_level.txt
softwareai-0.5.73.dist-info/RECORD
