Metadata-Version: 2.1
Name: softwareai
Version: 0.5.73
Summary: SoftwareAI is a framework with the aim of creating a software/application development company/organization governed by AI, its objective is not just to create the software with updates, documentation, schedules and spreadsheets, SoftwareAI is capable of running a software company completely with all the teams that make up a software company
Home-page: https://github.com/SoftwareAI-Company/SoftwareAI
Author: ualers
Author-email: freitasalexandre810@gmail.com
License: Apache License 2.0
Classifier: Programming Language :: Python :: 3
Classifier: License :: OSI Approved :: Apache Software License
Classifier: Operating System :: OS Independent
Requires-Python: >=3.7
License-File: LICENSE.txt
Requires-Dist: firebase-admin
Requires-Dist: asyncio
Requires-Dist: pandas
Requires-Dist: tiktoken
Requires-Dist: PyGithub
Requires-Dist: requests
Requires-Dist: python-dotenv
Requires-Dist: gitpython
Requires-Dist: openai
